README.md
setup.py
pgm/__init__.py
pgm/helpers/__init__.py
pgm/helpers/common.py
pgm/helpers/misc.py
pgm/helpers/search.py
pgm/helpers/trails.py
pgm/inference/Gibbs.py
pgm/inference/MetropolisHastings.py
pgm/inference/__init__.py
pgm/inference/check.py
pgm/inference/messageParsing.py
pgm/learning/__init__.py
pgm/representation/BN.py
pgm/representation/LinkedListBN.py
pgm/representation/LinkedListMN.py
pgm/representation/MN.py
pgm/representation/__init__.py
pgm/representation/algorithms/DAG.py
pgm/representation/algorithms/__init__.py
ppgm.egg-info/PKG-INFO
ppgm.egg-info/SOURCES.txt
ppgm.egg-info/dependency_links.txt
ppgm.egg-info/requires.txt
ppgm.egg-info/top_level.txt